{"title":"","description":"","date":"2026-02-14T15:45:53.592Z","order":1,"presenter":"Léa Salamé","authors":[""],"editor":"Elsa Pallot","editorDeputy":["Arnaud Comte","Margaux Manière","Julien Gasparutto"],"url":"","urlTvNews":"https://www.francetvinfo.fr/replay-jt/france-2/20-heures/jt-de-20h-du-mercredi-11-fevrier-2026_7757528.html","containsWordGlobalWarming":false}
{"title":"","description":"","date":"2026-02-14T15:45:53.653Z","order":1,"presenter":"Léa Salamé","authors":[""],"editor":"Elsa Pallot","editorDeputy":["Arnaud Comte","Margaux Manière","Julien Gasparutto"],"url":"","urlTvNews":"https://www.francetvinfo.fr/replay-jt/france-2/20-heures/jt-de-20h-du-mardi-10-fevrier-2026_7755197.html","containsWordGlobalWarming":false}
{"title":"","description":"","date":"2026-02-14T15:45:53.773Z","order":1,"presenter":"Laurent Delahousse","authors":[""],"editor":"Elsa Pallot","editorDeputy":["Arnaud Comte","Margaux Manière","Julien Gasparutto"],"url":"","urlTvNews":"https://www.francetvinfo.fr/replay-jt/france-2/20-heures/jt-de-20h-du-vendredi-13-fevrier-2026_7758134.html","containsWordGlobalWarming":false}
{"title":"","description":"","date":"2026-02-14T15:45:53.787Z","order":1,"presenter":"Léa Salamé","authors":[""],"editor":"Elsa Pallot","editorDeputy":["Arnaud Comte","Margaux Manière","Julien Gasparutto"],"url":"","urlTvNews":"https://www.francetvinfo.fr/replay-jt/france-2/20-heures/jt-de-20h-du-jeudi-12-fevrier-2026_7758137.html","containsWordGlobalWarming":false}
{"title":"","description":"","date":"2026-02-14T15:45:53.803Z","order":2,"presenter":"Léa Salamé","authors":[""],"editor":"Elsa Pallot","editorDeputy":["Arnaud Comte","Margaux Manière","Julien Gasparutto"],"url":"","urlTvNews":"https://www.francetvinfo.fr/replay-jt/france-2/20-heures/jt-de-20h-du-mercredi-11-fevrier-2026_7757528.html","containsWordGlobalWarming":false}
{"title":"","description":"","date":"2026-02-14T15:45:53.856Z","order":2,"presenter":"Léa Salamé","authors":[""],"editor":"Elsa Pallot","editorDeputy":["Arnaud Comte","Margaux Manière","Julien Gasparutto"],"url":"","urlTvNews":"https://www.francetvinfo.fr/replay-jt/france-2/20-heures/jt-de-20h-du-mardi-10-fevrier-2026_7755197.html","containsWordGlobalWarming":false}
{"title":"","description":"","date":"2026-02-14T15:45:53.919Z","order":1,"presenter":"Léa Salamé","authors":[""],"editor":"Elsa Pallot","editorDeputy":["Arnaud Comte","Margaux Manière","Julien Gasparutto"],"url":"","urlTvNews":"https://www.francetvinfo.fr/replay-jt/france-2/20-heures/jt-de-20h-du-lundi-9-fevrier-2026_7755239.html","containsWordGlobalWarming":false}
{"title":"","description":"","date":"2026-02-14T15:45:53.957Z","order":2,"presenter":"Laurent Delahousse","authors":[""],"editor":"Elsa Pallot","editorDeputy":["Arnaud Comte","Margaux Manière","Julien Gasparutto"],"url":"","urlTvNews":"https://www.francetvinfo.fr/replay-jt/france-2/20-heures/jt-de-20h-du-vendredi-13-fevrier-2026_7758134.html","containsWordGlobalWarming":false}
{"title":"","description":"","date":"2026-02-14T15:45:53.967Z","order":2,"presenter":"Léa Salamé","authors":[""],"editor":"Elsa Pallot","editorDeputy":["Arnaud Comte","Margaux Manière","Julien Gasparutto"],"url":"","urlTvNews":"https://www.francetvinfo.fr/replay-jt/france-2/20-heures/jt-de-20h-du-jeudi-12-fevrier-2026_7758137.html","containsWordGlobalWarming":false}
{"title":"","description":"","date":"2026-02-14T15:45:53.988Z","order":3,"presenter":"Léa Salamé","authors":[""],"editor":"Elsa Pallot","editorDeputy":["Arnaud Comte","Margaux Manière","Julien Gasparutto"],"url":"","urlTvNews":"https://www.francetvinfo.fr/replay-jt/france-2/20-heures/jt-de-20h-du-mercredi-11-fevrier-2026_7757528.html","containsWordGlobalWarming":false}
{"title":"","description":"","date":"2026-02-14T15:45:54.030Z","order":3,"presenter":"Léa Salamé","authors":[""],"editor":"Elsa Pallot","editorDeputy":["Arnaud Comte","Margaux Manière","Julien Gasparutto"],"url":"","urlTvNews":"https://www.francetvinfo.fr/replay-jt/france-2/20-heures/jt-de-20h-du-mardi-10-fevrier-2026_7755197.html","containsWordGlobalWarming":false}
{"title":"","description":"","date":"2026-02-14T15:45:54.154Z","order":2,"presenter":"Léa Salamé","authors":[""],"editor":"Elsa Pallot","editorDeputy":["Arnaud Comte","Margaux Manière","Julien Gasparutto"],"url":"","urlTvNews":"https://www.francetvinfo.fr/replay-jt/france-2/20-heures/jt-de-20h-du-lundi-9-fevrier-2026_7755239.html","containsWordGlobalWarming":false}
{"title":"","description":"","date":"2026-02-14T15:45:54.171Z","order":3,"presenter":"Léa Salamé","authors":[""],"editor":"Elsa Pallot","editorDeputy":["Arnaud Comte","Margaux Manière","Julien Gasparutto"],"url":"","urlTvNews":"https://www.francetvinfo.fr/replay-jt/france-2/20-heures/jt-de-20h-du-jeudi-12-fevrier-2026_7758137.html","containsWordGlobalWarming":false}
{"title":"","description":"","date":"2026-02-14T15:45:54.173Z","order":3,"presenter":"Laurent Delahousse","authors":[""],"editor":"Elsa Pallot","editorDeputy":["Arnaud Comte","Margaux Manière","Julien Gasparutto"],"url":"","urlTvNews":"https://www.francetvinfo.fr/replay-jt/france-2/20-heures/jt-de-20h-du-vendredi-13-fevrier-2026_7758134.html","containsWordGlobalWarming":false}
{"title":"","description":"","date":"2026-02-14T15:45:54.196Z","order":4,"presenter":"Léa Salamé","authors":[""],"editor":"Elsa Pallot","editorDeputy":["Arnaud Comte","Margaux Manière","Julien Gasparutto"],"url":"","urlTvNews":"https://www.francetvinfo.fr/replay-jt/france-2/20-heures/jt-de-20h-du-mercredi-11-fevrier-2026_7757528.html","containsWordGlobalWarming":false}
{"title":"","description":"","date":"2026-02-14T15:45:54.220Z","order":4,"presenter":"Léa Salamé","authors":[""],"editor":"Elsa Pallot","editorDeputy":["Arnaud Comte","Margaux Manière","Julien Gasparutto"],"url":"","urlTvNews":"https://www.francetvinfo.fr/replay-jt/france-2/20-heures/jt-de-20h-du-mardi-10-fevrier-2026_7755197.html","containsWordGlobalWarming":false}
{"title":"","description":"","date":"2026-02-14T15:45:54.313Z","order":4,"presenter":"Laurent Delahousse","authors":[""],"editor":"Elsa Pallot","editorDeputy":["Arnaud Comte","Margaux Manière","Julien Gasparutto"],"url":"","urlTvNews":"https://www.francetvinfo.fr/replay-jt/france-2/20-heures/jt-de-20h-du-vendredi-13-fevrier-2026_7758134.html","containsWordGlobalWarming":false}
{"title":"","description":"","date":"2026-02-14T15:45:54.364Z","order":4,"presenter":"Léa Salamé","authors":[""],"editor":"Elsa Pallot","editorDeputy":["Arnaud Comte","Margaux Manière","Julien Gasparutto"],"url":"","urlTvNews":"https://www.francetvinfo.fr/replay-jt/france-2/20-heures/jt-de-20h-du-jeudi-12-fevrier-2026_7758137.html","containsWordGlobalWarming":false}
{"title":"","description":"","date":"2026-02-14T15:45:54.377Z","order":3,"presenter":"Léa Salamé","authors":[""],"editor":"Elsa Pallot","editorDeputy":["Arnaud Comte","Margaux Manière","Julien Gasparutto"],"url":"","urlTvNews":"https://www.francetvinfo.fr/replay-jt/france-2/20-heures/jt-de-20h-du-lundi-9-fevrier-2026_7755239.html","containsWordGlobalWarming":false}
{"title":"","description":"","date":"2026-02-14T15:45:54.389Z","order":5,"presenter":"Léa Salamé","authors":[""],"editor":"Elsa Pallot","editorDeputy":["Arnaud Comte","Margaux Manière","Julien Gasparutto"],"url":"","urlTvNews":"https://www.francetvinfo.fr/replay-jt/france-2/20-heures/jt-de-20h-du-mercredi-11-fevrier-2026_7757528.html","containsWordGlobalWarming":false}
{"title":"","description":"","date":"2026-02-14T15:45:54.450Z","order":5,"presenter":"Léa Salamé","authors":[""],"editor":"Elsa Pallot","editorDeputy":["Arnaud Comte","Margaux Manière","Julien Gasparutto"],"url":"","urlTvNews":"https://www.francetvinfo.fr/replay-jt/france-2/20-heures/jt-de-20h-du-mardi-10-fevrier-2026_7755197.html","containsWordGlobalWarming":false}
{"title":"","description":"","date":"2026-02-14T15:45:54.465Z","order":5,"presenter":"Laurent Delahousse","authors":[""],"editor":"Elsa Pallot","editorDeputy":["Arnaud Comte","Margaux Manière","Julien Gasparutto"],"url":"","urlTvNews":"https://www.francetvinfo.fr/replay-jt/france-2/20-heures/jt-de-20h-du-vendredi-13-fevrier-2026_7758134.html","containsWordGlobalWarming":false}
{"title":"","description":"","date":"2026-02-14T15:45:54.514Z","order":5,"presenter":"Léa Salamé","authors":[""],"editor":"Elsa Pallot","editorDeputy":["Arnaud Comte","Margaux Manière","Julien Gasparutto"],"url":"","urlTvNews":"https://www.francetvinfo.fr/replay-jt/france-2/20-heures/jt-de-20h-du-jeudi-12-fevrier-2026_7758137.html","containsWordGlobalWarming":false}
{"title":"","description":"","date":"2026-02-14T15:45:54.516Z","order":4,"presenter":"Léa Salamé","authors":[""],"editor":"Elsa Pallot","editorDeputy":["Arnaud Comte","Margaux Manière","Julien Gasparutto"],"url":"","urlTvNews":"https://www.francetvinfo.fr/replay-jt/france-2/20-heures/jt-de-20h-du-lundi-9-fevrier-2026_7755239.html","containsWordGlobalWarming":false}
{"title":"","description":"","date":"2026-02-14T15:45:54.538Z","order":6,"presenter":"Léa Salamé","authors":[""],"editor":"Elsa Pallot","editorDeputy":["Arnaud Comte","Margaux Manière","Julien Gasparutto"],"url":"","urlTvNews":"https://www.francetvinfo.fr/replay-jt/france-2/20-heures/jt-de-20h-du-mercredi-11-fevrier-2026_7757528.html","containsWordGlobalWarming":false}
{"title":"","description":"","date":"2026-02-14T15:45:54.596Z","order":6,"presenter":"Léa Salamé","authors":[""],"editor":"Elsa Pallot","editorDeputy":["Arnaud Comte","Margaux Manière","Julien Gasparutto"],"url":"","urlTvNews":"https://www.francetvinfo.fr/replay-jt/france-2/20-heures/jt-de-20h-du-mardi-10-fevrier-2026_7755197.html","containsWordGlobalWarming":false}
{"title":"","description":"","date":"2026-02-14T15:45:54.623Z","order":6,"presenter":"Laurent Delahousse","authors":[""],"editor":"Elsa Pallot","editorDeputy":["Arnaud Comte","Margaux Manière","Julien Gasparutto"],"url":"","urlTvNews":"https://www.francetvinfo.fr/replay-jt/france-2/20-heures/jt-de-20h-du-vendredi-13-fevrier-2026_7758134.html","containsWordGlobalWarming":false}
{"title":"","description":"","date":"2026-02-14T15:45:54.641Z","order":6,"presenter":"Léa Salamé","authors":[""],"editor":"Elsa Pallot","editorDeputy":["Arnaud Comte","Margaux Manière","Julien Gasparutto"],"url":"","urlTvNews":"https://www.francetvinfo.fr/replay-jt/france-2/20-heures/jt-de-20h-du-jeudi-12-fevrier-2026_7758137.html","containsWordGlobalWarming":false}
{"title":"","description":"","date":"2026-02-14T15:45:54.668Z","order":5,"presenter":"Léa Salamé","authors":[""],"editor":"Elsa Pallot","editorDeputy":["Arnaud Comte","Margaux Manière","Julien Gasparutto"],"url":"","urlTvNews":"https://www.francetvinfo.fr/replay-jt/france-2/20-heures/jt-de-20h-du-lundi-9-fevrier-2026_7755239.html","containsWordGlobalWarming":false}
{"title":"","description":"","date":"2026-02-14T15:45:54.681Z","order":7,"presenter":"Léa Salamé","authors":[""],"editor":"Elsa Pallot","editorDeputy":["Arnaud Comte","Margaux Manière","Julien Gasparutto"],"url":"","urlTvNews":"https://www.francetvinfo.fr/replay-jt/france-2/20-heures/jt-de-20h-du-mercredi-11-fevrier-2026_7757528.html","containsWordGlobalWarming":false}
{"title":"","description":"","date":"2026-02-14T15:45:54.726Z","order":7,"presenter":"Léa Salamé","authors":[""],"editor":"Elsa Pallot","editorDeputy":["Arnaud Comte","Margaux Manière","Julien Gasparutto"],"url":"","urlTvNews":"https://www.francetvinfo.fr/replay-jt/france-2/20-heures/jt-de-20h-du-mardi-10-fevrier-2026_7755197.html","containsWordGlobalWarming":false}
{"title":"","description":"","date":"2026-02-14T15:45:54.776Z","order":7,"presenter":"Laurent Delahousse","authors":[""],"editor":"Elsa Pallot","editorDeputy":["Arnaud Comte","Margaux Manière","Julien Gasparutto"],"url":"","urlTvNews":"https://www.francetvinfo.fr/replay-jt/france-2/20-heures/jt-de-20h-du-vendredi-13-fevrier-2026_7758134.html","containsWordGlobalWarming":false}
{"title":"","description":"","date":"2026-02-14T15:45:54.791Z","order":6,"presenter":"Léa Salamé","authors":[""],"editor":"Elsa Pallot","editorDeputy":["Arnaud Comte","Margaux Manière","Julien Gasparutto"],"url":"","urlTvNews":"https://www.francetvinfo.fr/replay-jt/france-2/20-heures/jt-de-20h-du-lundi-9-fevrier-2026_7755239.html","containsWordGlobalWarming":false}
{"title":"","description":"","date":"2026-02-14T15:45:54.819Z","order":7,"presenter":"Léa Salamé","authors":[""],"editor":"Elsa Pallot","editorDeputy":["Arnaud Comte","Margaux Manière","Julien Gasparutto"],"url":"","urlTvNews":"https://www.francetvinfo.fr/replay-jt/france-2/20-heures/jt-de-20h-du-jeudi-12-fevrier-2026_7758137.html","containsWordGlobalWarming":false}
{"title":"","description":"","date":"2026-02-14T15:45:54.830Z","order":8,"presenter":"Léa Salamé","authors":[""],"editor":"Elsa Pallot","editorDeputy":["Arnaud Comte","Margaux Manière","Julien Gasparutto"],"url":"","urlTvNews":"https://www.francetvinfo.fr/replay-jt/france-2/20-heures/jt-de-20h-du-mercredi-11-fevrier-2026_7757528.html","containsWordGlobalWarming":false}
{"title":"","description":"","date":"2026-02-14T15:45:54.850Z","order":8,"presenter":"Léa Salamé","authors":[""],"editor":"Elsa Pallot","editorDeputy":["Arnaud Comte","Margaux Manière","Julien Gasparutto"],"url":"","urlTvNews":"https://www.francetvinfo.fr/replay-jt/france-2/20-heures/jt-de-20h-du-mardi-10-fevrier-2026_7755197.html","containsWordGlobalWarming":false}
{"title":"","description":"","date":"2026-02-14T15:45:54.913Z","order":8,"presenter":"Laurent Delahousse","authors":[""],"editor":"Elsa Pallot","editorDeputy":["Arnaud Comte","Margaux Manière","Julien Gasparutto"],"url":"","urlTvNews":"https://www.francetvinfo.fr/replay-jt/france-2/20-heures/jt-de-20h-du-vendredi-13-fevrier-2026_7758134.html","containsWordGlobalWarming":false}
{"title":"","description":"","date":"2026-02-14T15:45:54.967Z","order":9,"presenter":"Léa Salamé","authors":[""],"editor":"Elsa Pallot","editorDeputy":["Arnaud Comte","Margaux Manière","Julien Gasparutto"],"url":"","urlTvNews":"https://www.francetvinfo.fr/replay-jt/france-2/20-heures/jt-de-20h-du-mercredi-11-fevrier-2026_7757528.html","containsWordGlobalWarming":false}
{"title":"","description":"","date":"2026-02-14T15:45:54.992Z","order":7,"presenter":"Léa Salamé","authors":[""],"editor":"Elsa Pallot","editorDeputy":["Arnaud Comte","Margaux Manière","Julien Gasparutto"],"url":"","urlTvNews":"https://www.francetvinfo.fr/replay-jt/france-2/20-heures/jt-de-20h-du-lundi-9-fevrier-2026_7755239.html","containsWordGlobalWarming":false}
{"title":"","description":"","date":"2026-02-14T15:45:54.994Z","order":8,"presenter":"Léa Salamé","authors":[""],"editor":"Elsa Pallot","editorDeputy":["Arnaud Comte","Margaux Manière","Julien Gasparutto"],"url":"","urlTvNews":"https://www.francetvinfo.fr/replay-jt/france-2/20-heures/jt-de-20h-du-jeudi-12-fevrier-2026_7758137.html","containsWordGlobalWarming":false}
{"title":"","description":"","date":"2026-02-14T15:45:55.000Z","order":9,"presenter":"Léa Salamé","authors":[""],"editor":"Elsa Pallot","editorDeputy":["Arnaud Comte","Margaux Manière","Julien Gasparutto"],"url":"","urlTvNews":"https://www.francetvinfo.fr/replay-jt/france-2/20-heures/jt-de-20h-du-mardi-10-fevrier-2026_7755197.html","containsWordGlobalWarming":false}
{"title":"","description":"","date":"2026-02-14T15:45:55.054Z","order":9,"presenter":"Laurent Delahousse","authors":[""],"editor":"Elsa Pallot","editorDeputy":["Arnaud Comte","Margaux Manière","Julien Gasparutto"],"url":"","urlTvNews":"https://www.francetvinfo.fr/replay-jt/france-2/20-heures/jt-de-20h-du-vendredi-13-fevrier-2026_7758134.html","containsWordGlobalWarming":false}
{"title":"","description":"","date":"2026-02-14T15:45:55.120Z","order":10,"presenter":"Léa Salamé","authors":[""],"editor":"Elsa Pallot","editorDeputy":["Arnaud Comte","Margaux Manière","Julien Gasparutto"],"url":"","urlTvNews":"https://www.francetvinfo.fr/replay-jt/france-2/20-heures/jt-de-20h-du-mercredi-11-fevrier-2026_7757528.html","containsWordGlobalWarming":false}
{"title":"","description":"","date":"2026-02-14T15:45:55.128Z","order":8,"presenter":"Léa Salamé","authors":[""],"editor":"Elsa Pallot","editorDeputy":["Arnaud Comte","Margaux Manière","Julien Gasparutto"],"url":"","urlTvNews":"https://www.francetvinfo.fr/replay-jt/france-2/20-heures/jt-de-20h-du-lundi-9-fevrier-2026_7755239.html","containsWordGlobalWarming":false}
{"title":"","description":"","date":"2026-02-14T15:45:55.156Z","order":10,"presenter":"Léa Salamé","authors":[""],"editor":"Elsa Pallot","editorDeputy":["Arnaud Comte","Margaux Manière","Julien Gasparutto"],"url":"","urlTvNews":"https://www.francetvinfo.fr/replay-jt/france-2/20-heures/jt-de-20h-du-mardi-10-fevrier-2026_7755197.html","containsWordGlobalWarming":false}
{"title":"","description":"","date":"2026-02-14T15:45:55.182Z","order":9,"presenter":"Léa Salamé","authors":[""],"editor":"Elsa Pallot","editorDeputy":["Arnaud Comte","Margaux Manière","Julien Gasparutto"],"url":"","urlTvNews":"https://www.francetvinfo.fr/replay-jt/france-2/20-heures/jt-de-20h-du-jeudi-12-fevrier-2026_7758137.html","containsWordGlobalWarming":false}
{"title":"","description":"","date":"2026-02-14T15:45:55.202Z","order":10,"presenter":"Laurent Delahousse","authors":[""],"editor":"Elsa Pallot","editorDeputy":["Arnaud Comte","Margaux Manière","Julien Gasparutto"],"url":"","urlTvNews":"https://www.francetvinfo.fr/replay-jt/france-2/20-heures/jt-de-20h-du-vendredi-13-fevrier-2026_7758134.html","containsWordGlobalWarming":false}
{"title":"","description":"","date":"2026-02-14T15:45:55.218Z","order":9,"presenter":"Léa Salamé","authors":[""],"editor":"Elsa Pallot","editorDeputy":["Arnaud Comte","Margaux Manière","Julien Gasparutto"],"url":"","urlTvNews":"https://www.francetvinfo.fr/replay-jt/france-2/20-heures/jt-de-20h-du-lundi-9-fevrier-2026_7755239.html","containsWordGlobalWarming":false}
{"title":"","description":"","date":"2026-02-14T15:45:55.280Z","order":10,"presenter":"Léa Salamé","authors":[""],"editor":"Elsa Pallot","editorDeputy":["Arnaud Comte","Margaux Manière","Julien Gasparutto"],"url":"","urlTvNews":"https://www.francetvinfo.fr/replay-jt/france-2/20-heures/jt-de-20h-du-jeudi-12-fevrier-2026_7758137.html","containsWordGlobalWarming":false}
{"title":"","description":"","date":"2026-02-14T15:45:55.286Z","order":11,"presenter":"Léa Salamé","authors":[""],"editor":"Elsa Pallot","editorDeputy":["Arnaud Comte","Margaux Manière","Julien Gasparutto"],"url":"","urlTvNews":"https://www.francetvinfo.fr/replay-jt/france-2/20-heures/jt-de-20h-du-mardi-10-fevrier-2026_7755197.html","containsWordGlobalWarming":false}
{"title":"","description":"","date":"2026-02-14T15:45:55.309Z","order":11,"presenter":"Laurent Delahousse","authors":[""],"editor":"Elsa Pallot","editorDeputy":["Arnaud Comte","Margaux Manière","Julien Gasparutto"],"url":"","urlTvNews":"https://www.francetvinfo.fr/replay-jt/france-2/20-heures/jt-de-20h-du-vendredi-13-fevrier-2026_7758134.html","containsWordGlobalWarming":false}
{"title":"","description":"","date":"2026-02-14T15:45:55.329Z","order":10,"presenter":"Léa Salamé","authors":[""],"editor":"Elsa Pallot","editorDeputy":["Arnaud Comte","Margaux Manière","Julien Gasparutto"],"url":"","urlTvNews":"https://www.francetvinfo.fr/replay-jt/france-2/20-heures/jt-de-20h-du-lundi-9-fevrier-2026_7755239.html","containsWordGlobalWarming":false}
{"title":"","description":"","date":"2026-02-14T15:45:55.399Z","order":11,"presenter":"Léa Salamé","authors":[""],"editor":"Elsa Pallot","editorDeputy":["Arnaud Comte","Margaux Manière","Julien Gasparutto"],"url":"","urlTvNews":"https://www.francetvinfo.fr/replay-jt/france-2/20-heures/jt-de-20h-du-jeudi-12-fevrier-2026_7758137.html","containsWordGlobalWarming":false}
{"title":"","description":"","date":"2026-02-14T15:45:55.403Z","order":12,"presenter":"Laurent Delahousse","authors":[""],"editor":"Elsa Pallot","editorDeputy":["Arnaud Comte","Margaux Manière","Julien Gasparutto"],"url":"","urlTvNews":"https://www.francetvinfo.fr/replay-jt/france-2/20-heures/jt-de-20h-du-vendredi-13-fevrier-2026_7758134.html","containsWordGlobalWarming":false}
{"title":"","description":"","date":"2026-02-14T15:45:55.416Z","order":11,"presenter":"Léa Salamé","authors":[""],"editor":"Elsa Pallot","editorDeputy":["Arnaud Comte","Margaux Manière","Julien Gasparutto"],"url":"","urlTvNews":"https://www.francetvinfo.fr/replay-jt/france-2/20-heures/jt-de-20h-du-lundi-9-fevrier-2026_7755239.html","containsWordGlobalWarming":false}
{"title":"","description":"","date":"2026-02-14T15:45:55.427Z","order":12,"presenter":"Léa Salamé","authors":[""],"editor":"Elsa Pallot","editorDeputy":["Arnaud Comte","Margaux Manière","Julien Gasparutto"],"url":"","urlTvNews":"https://www.francetvinfo.fr/replay-jt/france-2/20-heures/jt-de-20h-du-mardi-10-fevrier-2026_7755197.html","containsWordGlobalWarming":false}
{"title":"","description":"","date":"2026-02-14T15:45:55.522Z","order":13,"presenter":"Laurent Delahousse","authors":[""],"editor":"Elsa Pallot","editorDeputy":["Arnaud Comte","Margaux Manière","Julien Gasparutto"],"url":"","urlTvNews":"https://www.francetvinfo.fr/replay-jt/france-2/20-heures/jt-de-20h-du-vendredi-13-fevrier-2026_7758134.html","containsWordGlobalWarming":false}
{"title":"","description":"","date":"2026-02-14T15:45:55.528Z","order":12,"presenter":"Léa Salamé","authors":[""],"editor":"Elsa Pallot","editorDeputy":["Arnaud Comte","Margaux Manière","Julien Gasparutto"],"url":"","urlTvNews":"https://www.francetvinfo.fr/replay-jt/france-2/20-heures/jt-de-20h-du-jeudi-12-fevrier-2026_7758137.html","containsWordGlobalWarming":false}
{"title":"","description":"","date":"2026-02-14T15:45:55.540Z","order":12,"presenter":"Léa Salamé","authors":[""],"editor":"Elsa Pallot","editorDeputy":["Arnaud Comte","Margaux Manière","Julien Gasparutto"],"url":"","urlTvNews":"https://www.francetvinfo.fr/replay-jt/france-2/20-heures/jt-de-20h-du-lundi-9-fevrier-2026_7755239.html","containsWordGlobalWarming":false}
{"title":"","description":"","date":"2026-02-14T15:45:55.543Z","order":13,"presenter":"Léa Salamé","authors":[""],"editor":"Elsa Pallot","editorDeputy":["Arnaud Comte","Margaux Manière","Julien Gasparutto"],"url":"","urlTvNews":"https://www.francetvinfo.fr/replay-jt/france-2/20-heures/jt-de-20h-du-mardi-10-fevrier-2026_7755197.html","containsWordGlobalWarming":false}
{"title":"","description":"","date":"2026-02-14T15:45:55.635Z","order":13,"presenter":"Léa Salamé","authors":[""],"editor":"Elsa Pallot","editorDeputy":["Arnaud Comte","Margaux Manière","Julien Gasparutto"],"url":"","urlTvNews":"https://www.francetvinfo.fr/replay-jt/france-2/20-heures/jt-de-20h-du-lundi-9-fevrier-2026_7755239.html","containsWordGlobalWarming":false}
{"title":"","description":"","date":"2026-02-14T15:45:55.747Z","order":14,"presenter":"Léa Salamé","authors":[""],"editor":"Elsa Pallot","editorDeputy":["Arnaud Comte","Margaux Manière","Julien Gasparutto"],"url":"","urlTvNews":"https://www.francetvinfo.fr/replay-jt/france-2/20-heures/jt-de-20h-du-lundi-9-fevrier-2026_7755239.html","containsWordGlobalWarming":false}
{"title":"","description":"","date":"2026-02-14T15:45:55.818Z","order":15,"presenter":"Léa Salamé","authors":[""],"editor":"Elsa Pallot","editorDeputy":["Arnaud Comte","Margaux Manière","Julien Gasparutto"],"url":"","urlTvNews":"https://www.francetvinfo.fr/replay-jt/france-2/20-heures/jt-de-20h-du-lundi-9-fevrier-2026_7755239.html","containsWordGlobalWarming":false}
{"title":"","description":"","date":"2026-02-14T15:45:55.921Z","order":16,"presenter":"Léa Salamé","authors":[""],"editor":"Elsa Pallot","editorDeputy":["Arnaud Comte","Margaux Manière","Julien Gasparutto"],"url":"","urlTvNews":"https://www.francetvinfo.fr/replay-jt/france-2/20-heures/jt-de-20h-du-lundi-9-fevrier-2026_7755239.html","containsWordGlobalWarming":false}
{"title":"","description":"","date":"2026-02-14T15:45:57.270Z","order":1,"presenter":"Julian Bugier","authors":[""],"editor":"Elsa Pallot","editorDeputy":["Arnaud Comte","Margaux Manière","Julien Gasparutto"],"url":"","urlTvNews":"https://www.francetvinfo.fr/replay-jt/france-2/13-heures/jt-de-13h-du-mardi-10-fevrier-2026_7755215.html","containsWordGlobalWarming":false}
{"title":"","description":"","date":"2026-02-14T15:45:57.349Z","order":2,"presenter":"Julian Bugier","authors":[""],"editor":"Elsa Pallot","editorDeputy":["Arnaud Comte","Margaux Manière","Julien Gasparutto"],"url":"","urlTvNews":"https://www.francetvinfo.fr/replay-jt/france-2/13-heures/jt-de-13h-du-mardi-10-fevrier-2026_7755215.html","containsWordGlobalWarming":false}
{"title":"","description":"","date":"2026-02-14T15:45:57.455Z","order":3,"presenter":"Julian Bugier","authors":[""],"editor":"Elsa Pallot","editorDeputy":["Arnaud Comte","Margaux Manière","Julien Gasparutto"],"url":"","urlTvNews":"https://www.francetvinfo.fr/replay-jt/france-2/13-heures/jt-de-13h-du-mardi-10-fevrier-2026_7755215.html","containsWordGlobalWarming":false}
{"title":"","description":"","date":"2026-02-14T15:45:57.458Z","order":1,"presenter":"Julian Bugier","authors":[""],"editor":"Elsa Pallot","editorDeputy":["Arnaud Comte","Margaux Manière","Julien Gasparutto"],"url":"","urlTvNews":"https://www.francetvinfo.fr/replay-jt/france-2/13-heures/jt-de-13h-du-mercredi-11-fevrier-2026_7757534.html","containsWordGlobalWarming":false}
{"title":"","description":"","date":"2026-02-14T15:45:57.519Z","order":1,"presenter":"Julian Bugier","authors":[""],"editor":"Elsa Pallot","editorDeputy":["Arnaud Comte","Margaux Manière","Julien Gasparutto"],"url":"","urlTvNews":"https://www.francetvinfo.fr/replay-jt/france-2/13-heures/jt-de-13h-du-vendredi-13-fevrier-2026_7758149.html","containsWordGlobalWarming":false}
{"title":"","description":"","date":"2026-02-14T15:45:57.539Z","order":4,"presenter":"Julian Bugier","authors":[""],"editor":"Elsa Pallot","editorDeputy":["Arnaud Comte","Margaux Manière","Julien Gasparutto"],"url":"","urlTvNews":"https://www.francetvinfo.fr/replay-jt/france-2/13-heures/jt-de-13h-du-mardi-10-fevrier-2026_7755215.html","containsWordGlobalWarming":false}
{"title":"","description":"","date":"2026-02-14T15:45:57.561Z","order":2,"presenter":"Julian Bugier","authors":[""],"editor":"Elsa Pallot","editorDeputy":["Arnaud Comte","Margaux Manière","Julien Gasparutto"],"url":"","urlTvNews":"https://www.francetvinfo.fr/replay-jt/france-2/13-heures/jt-de-13h-du-mercredi-11-fevrier-2026_7757534.html","containsWordGlobalWarming":false}
{"title":"","description":"","date":"2026-02-14T15:45:57.593Z","order":2,"presenter":"Julian Bugier","authors":[""],"editor":"Elsa Pallot","editorDeputy":["Arnaud Comte","Margaux Manière","Julien Gasparutto"],"url":"","urlTvNews":"https://www.francetvinfo.fr/replay-jt/france-2/13-heures/jt-de-13h-du-vendredi-13-fevrier-2026_7758149.html","containsWordGlobalWarming":false}
{"title":"","description":"","date":"2026-02-14T15:45:57.632Z","order":3,"presenter":"Julian Bugier","authors":[""],"editor":"Elsa Pallot","editorDeputy":["Arnaud Comte","Margaux Manière","Julien Gasparutto"],"url":"","urlTvNews":"https://www.francetvinfo.fr/replay-jt/france-2/13-heures/jt-de-13h-du-mercredi-11-fevrier-2026_7757534.html","containsWordGlobalWarming":false}
{"title":"","description":"","date":"2026-02-14T15:45:57.658Z","order":5,"presenter":"Julian Bugier","authors":[""],"editor":"Elsa Pallot","editorDeputy":["Arnaud Comte","Margaux Manière","Julien Gasparutto"],"url":"","urlTvNews":"https://www.francetvinfo.fr/replay-jt/france-2/13-heures/jt-de-13h-du-mardi-10-fevrier-2026_7755215.html","containsWordGlobalWarming":false}
{"title":"","description":"","date":"2026-02-14T15:45:57.672Z","order":3,"presenter":"Julian Bugier","authors":[""],"editor":"Elsa Pallot","editorDeputy":["Arnaud Comte","Margaux Manière","Julien Gasparutto"],"url":"","urlTvNews":"https://www.francetvinfo.fr/replay-jt/france-2/13-heures/jt-de-13h-du-vendredi-13-fevrier-2026_7758149.html","containsWordGlobalWarming":false}
{"title":"","description":"","date":"2026-02-14T15:45:57.700Z","order":4,"presenter":"Julian Bugier","authors":[""],"editor":"Elsa Pallot","editorDeputy":["Arnaud Comte","Margaux Manière","Julien Gasparutto"],"url":"","urlTvNews":"https://www.francetvinfo.fr/replay-jt/france-2/13-heures/jt-de-13h-du-mercredi-11-fevrier-2026_7757534.html","containsWordGlobalWarming":false}
{"title":"","description":"","date":"2026-02-14T15:45:57.731Z","order":6,"presenter":"Julian Bugier","authors":[""],"editor":"Elsa Pallot","editorDeputy":["Arnaud Comte","Margaux Manière","Julien Gasparutto"],"url":"","urlTvNews":"https://www.francetvinfo.fr/replay-jt/france-2/13-heures/jt-de-13h-du-mardi-10-fevrier-2026_7755215.html","containsWordGlobalWarming":false}
{"title":"","description":"","date":"2026-02-14T15:45:57.746Z","order":4,"presenter":"Julian Bugier","authors":[""],"editor":"Elsa Pallot","editorDeputy":["Arnaud Comte","Margaux Manière","Julien Gasparutto"],"url":"","urlTvNews":"https://www.francetvinfo.fr/replay-jt/france-2/13-heures/jt-de-13h-du-vendredi-13-fevrier-2026_7758149.html","containsWordGlobalWarming":false}
{"title":"","description":"","date":"2026-02-14T15:45:57.772Z","order":5,"presenter":"Julian Bugier","authors":[""],"editor":"Elsa Pallot","editorDeputy":["Arnaud Comte","Margaux Manière","Julien Gasparutto"],"url":"","urlTvNews":"https://www.francetvinfo.fr/replay-jt/france-2/13-heures/jt-de-13h-du-mercredi-11-fevrier-2026_7757534.html","containsWordGlobalWarming":false}
{"title":"","description":"","date":"2026-02-14T15:45:57.805Z","order":7,"presenter":"Julian Bugier","authors":[""],"editor":"Elsa Pallot","editorDeputy":["Arnaud Comte","Margaux Manière","Julien Gasparutto"],"url":"","urlTvNews":"https://www.francetvinfo.fr/replay-jt/france-2/13-heures/jt-de-13h-du-mardi-10-fevrier-2026_7755215.html","containsWordGlobalWarming":false}
{"title":"","description":"","date":"2026-02-14T15:45:57.845Z","order":5,"presenter":"Julian Bugier","authors":[""],"editor":"Elsa Pallot","editorDeputy":["Arnaud Comte","Margaux Manière","Julien Gasparutto"],"url":"","urlTvNews":"https://www.francetvinfo.fr/replay-jt/france-2/13-heures/jt-de-13h-du-vendredi-13-fevrier-2026_7758149.html","containsWordGlobalWarming":false}
{"title":"","description":"","date":"2026-02-14T15:45:57.855Z","order":6,"presenter":"Julian Bugier","authors":[""],"editor":"Elsa Pallot","editorDeputy":["Arnaud Comte","Margaux Manière","Julien Gasparutto"],"url":"","urlTvNews":"https://www.francetvinfo.fr/replay-jt/france-2/13-heures/jt-de-13h-du-mercredi-11-fevrier-2026_7757534.html","containsWordGlobalWarming":false}
{"title":"","description":"","date":"2026-02-14T15:45:57.894Z","order":8,"presenter":"Julian Bugier","authors":[""],"editor":"Elsa Pallot","editorDeputy":["Arnaud Comte","Margaux Manière","Julien Gasparutto"],"url":"","urlTvNews":"https://www.francetvinfo.fr/replay-jt/france-2/13-heures/jt-de-13h-du-mardi-10-fevrier-2026_7755215.html","containsWordGlobalWarming":false}
{"title":"","description":"","date":"2026-02-14T15:45:57.925Z","order":7,"presenter":"Julian Bugier","authors":[""],"editor":"Elsa Pallot","editorDeputy":["Arnaud Comte","Margaux Manière","Julien Gasparutto"],"url":"","urlTvNews":"https://www.francetvinfo.fr/replay-jt/france-2/13-heures/jt-de-13h-du-mercredi-11-fevrier-2026_7757534.html","containsWordGlobalWarming":false}
{"title":"","description":"","date":"2026-02-14T15:45:57.933Z","order":6,"presenter":"Julian Bugier","authors":[""],"editor":"Elsa Pallot","editorDeputy":["Arnaud Comte","Margaux Manière","Julien Gasparutto"],"url":"","urlTvNews":"https://www.francetvinfo.fr/replay-jt/france-2/13-heures/jt-de-13h-du-vendredi-13-fevrier-2026_7758149.html","containsWordGlobalWarming":false}
{"title":"","description":"","date":"2026-02-14T15:45:57.980Z","order":9,"presenter":"Julian Bugier","authors":[""],"editor":"Elsa Pallot","editorDeputy":["Arnaud Comte","Margaux Manière","Julien Gasparutto"],"url":"","urlTvNews":"https://www.francetvinfo.fr/replay-jt/france-2/13-heures/jt-de-13h-du-mardi-10-fevrier-2026_7755215.html","containsWordGlobalWarming":false}
{"title":"","description":"","date":"2026-02-14T15:45:58.016Z","order":8,"presenter":"Julian Bugier","authors":[""],"editor":"Elsa Pallot","editorDeputy":["Arnaud Comte","Margaux Manière","Julien Gasparutto"],"url":"","urlTvNews":"https://www.francetvinfo.fr/replay-jt/france-2/13-heures/jt-de-13h-du-mercredi-11-fevrier-2026_7757534.html","containsWordGlobalWarming":false}
{"title":"","description":"","date":"2026-02-14T15:45:58.020Z","order":7,"presenter":"Julian Bugier","authors":[""],"editor":"Elsa Pallot","editorDeputy":["Arnaud Comte","Margaux Manière","Julien Gasparutto"],"url":"","urlTvNews":"https://www.francetvinfo.fr/replay-jt/france-2/13-heures/jt-de-13h-du-vendredi-13-fevrier-2026_7758149.html","containsWordGlobalWarming":false}
{"title":"","description":"","date":"2026-02-14T15:45:58.093Z","order":8,"presenter":"Julian Bugier","authors":[""],"editor":"Elsa Pallot","editorDeputy":["Arnaud Comte","Margaux Manière","Julien Gasparutto"],"url":"","urlTvNews":"https://www.francetvinfo.fr/replay-jt/france-2/13-heures/jt-de-13h-du-vendredi-13-fevrier-2026_7758149.html","containsWordGlobalWarming":false}
{"title":"","description":"","date":"2026-02-14T15:45:58.135Z","order":9,"presenter":"Julian Bugier","authors":[""],"editor":"Elsa Pallot","editorDeputy":["Arnaud Comte","Margaux Manière","Julien Gasparutto"],"url":"","urlTvNews":"https://www.francetvinfo.fr/replay-jt/france-2/13-heures/jt-de-13h-du-mercredi-11-fevrier-2026_7757534.html","containsWordGlobalWarming":false}
{"title":"","description":"","date":"2026-02-14T15:45:58.225Z","order":10,"presenter":"Julian Bugier","authors":[""],"editor":"Elsa Pallot","editorDeputy":["Arnaud Comte","Margaux Manière","Julien Gasparutto"],"url":"","urlTvNews":"https://www.francetvinfo.fr/replay-jt/france-2/13-heures/jt-de-13h-du-mercredi-11-fevrier-2026_7757534.html","containsWordGlobalWarming":false}
{"title":"","description":"","date":"2026-02-14T15:45:58.231Z","order":9,"presenter":"Julian Bugier","authors":[""],"editor":"Elsa Pallot","editorDeputy":["Arnaud Comte","Margaux Manière","Julien Gasparutto"],"url":"","urlTvNews":"https://www.francetvinfo.fr/replay-jt/france-2/13-heures/jt-de-13h-du-vendredi-13-fevrier-2026_7758149.html","containsWordGlobalWarming":false}
{"title":"","description":"","date":"2026-02-14T15:45:58.307Z","order":10,"presenter":"Julian Bugier","authors":[""],"editor":"Elsa Pallot","editorDeputy":["Arnaud Comte","Margaux Manière","Julien Gasparutto"],"url":"","urlTvNews":"https://www.francetvinfo.fr/replay-jt/france-2/13-heures/jt-de-13h-du-vendredi-13-fevrier-2026_7758149.html","containsWordGlobalWarming":false}
{"title":"","description":"","date":"2026-02-14T15:45:58.337Z","order":11,"presenter":"Julian Bugier","authors":[""],"editor":"Elsa Pallot","editorDeputy":["Arnaud Comte","Margaux Manière","Julien Gasparutto"],"url":"","urlTvNews":"https://www.francetvinfo.fr/replay-jt/france-2/13-heures/jt-de-13h-du-mercredi-11-fevrier-2026_7757534.html","containsWordGlobalWarming":false}
{"title":"","description":"","date":"2026-02-14T15:45:58.381Z","order":11,"presenter":"Julian Bugier","authors":[""],"editor":"Elsa Pallot","editorDeputy":["Arnaud Comte","Margaux Manière","Julien Gasparutto"],"url":"","urlTvNews":"https://www.francetvinfo.fr/replay-jt/france-2/13-heures/jt-de-13h-du-vendredi-13-fevrier-2026_7758149.html","containsWordGlobalWarming":false}
{"title":"","description":"","date":"2026-02-14T15:45:58.417Z","order":12,"presenter":"Julian Bugier","authors":[""],"editor":"Elsa Pallot","editorDeputy":["Arnaud Comte","Margaux Manière","Julien Gasparutto"],"url":"","urlTvNews":"https://www.francetvinfo.fr/replay-jt/france-2/13-heures/jt-de-13h-du-mercredi-11-fevrier-2026_7757534.html","containsWordGlobalWarming":false}
{"title":"","description":"","date":"2026-02-14T15:45:58.572Z","order":12,"presenter":"Julian Bugier","authors":[""],"editor":"Elsa Pallot","editorDeputy":["Arnaud Comte","Margaux Manière","Julien Gasparutto"],"url":"","urlTvNews":"https://www.francetvinfo.fr/replay-jt/france-2/13-heures/jt-de-13h-du-vendredi-13-fevrier-2026_7758149.html","containsWordGlobalWarming":false}
{"title":"","description":"","date":"2026-02-14T15:45:58.768Z","order":13,"presenter":"Julian Bugier","authors":[""],"editor":"Elsa Pallot","editorDeputy":["Arnaud Comte","Margaux Manière","Julien Gasparutto"],"url":"","urlTvNews":"https://www.francetvinfo.fr/replay-jt/france-2/13-heures/jt-de-13h-du-vendredi-13-fevrier-2026_7758149.html","containsWordGlobalWarming":false}
{"title":"","description":"","date":"2026-02-14T15:45:58.863Z","order":14,"presenter":"Julian Bugier","authors":[""],"editor":"Elsa Pallot","editorDeputy":["Arnaud Comte","Margaux Manière","Julien Gasparutto"],"url":"","urlTvNews":"https://www.francetvinfo.fr/replay-jt/france-2/13-heures/jt-de-13h-du-vendredi-13-fevrier-2026_7758149.html","containsWordGlobalWarming":false}
{"title":"","description":"","date":"2026-02-14T15:46:00.262Z","order":1,"presenter":"Julian Bugier","authors":[""],"editor":"Elsa Pallot","editorDeputy":["Arnaud Comte","Margaux Manière","Julien Gasparutto"],"url":"","urlTvNews":"https://www.francetvinfo.fr/replay-jt/france-2/13-heures/jt-de-13h-du-jeudi-12-fevrier-2026_7758155.html","containsWordGlobalWarming":false}
{"title":"","description":"","date":"2026-02-14T15:46:00.332Z","order":2,"presenter":"Julian Bugier","authors":[""],"editor":"Elsa Pallot","editorDeputy":["Arnaud Comte","Margaux Manière","Julien Gasparutto"],"url":"","urlTvNews":"https://www.francetvinfo.fr/replay-jt/france-2/13-heures/jt-de-13h-du-jeudi-12-fevrier-2026_7758155.html","containsWordGlobalWarming":false}
{"title":"","description":"","date":"2026-02-14T15:46:00.405Z","order":3,"presenter":"Julian Bugier","authors":[""],"editor":"Elsa Pallot","editorDeputy":["Arnaud Comte","Margaux Manière","Julien Gasparutto"],"url":"","urlTvNews":"https://www.francetvinfo.fr/replay-jt/france-2/13-heures/jt-de-13h-du-jeudi-12-fevrier-2026_7758155.html","containsWordGlobalWarming":false}
{"title":"","description":"","date":"2026-02-14T15:46:00.483Z","order":4,"presenter":"Julian Bugier","authors":[""],"editor":"Elsa Pallot","editorDeputy":["Arnaud Comte","Margaux Manière","Julien Gasparutto"],"url":"","urlTvNews":"https://www.francetvinfo.fr/replay-jt/france-2/13-heures/jt-de-13h-du-jeudi-12-fevrier-2026_7758155.html","containsWordGlobalWarming":false}
{"title":"","description":"","date":"2026-02-14T15:46:00.559Z","order":5,"presenter":"Julian Bugier","authors":[""],"editor":"Elsa Pallot","editorDeputy":["Arnaud Comte","Margaux Manière","Julien Gasparutto"],"url":"","urlTvNews":"https://www.francetvinfo.fr/replay-jt/france-2/13-heures/jt-de-13h-du-jeudi-12-fevrier-2026_7758155.html","containsWordGlobalWarming":false}
{"title":"","description":"","date":"2026-02-14T15:46:00.650Z","order":6,"presenter":"Julian Bugier","authors":[""],"editor":"Elsa Pallot","editorDeputy":["Arnaud Comte","Margaux Manière","Julien Gasparutto"],"url":"","urlTvNews":"https://www.francetvinfo.fr/replay-jt/france-2/13-heures/jt-de-13h-du-jeudi-12-fevrier-2026_7758155.html","containsWordGlobalWarming":false}
{"title":"","description":"","date":"2026-02-14T15:46:00.725Z","order":7,"presenter":"Julian Bugier","authors":[""],"editor":"Elsa Pallot","editorDeputy":["Arnaud Comte","Margaux Manière","Julien Gasparutto"],"url":"","urlTvNews":"https://www.francetvinfo.fr/replay-jt/france-2/13-heures/jt-de-13h-du-jeudi-12-fevrier-2026_7758155.html","containsWordGlobalWarming":false}
{"title":"","description":"","date":"2026-02-14T15:46:00.800Z","order":8,"presenter":"Julian Bugier","authors":[""],"editor":"Elsa Pallot","editorDeputy":["Arnaud Comte","Margaux Manière","Julien Gasparutto"],"url":"","urlTvNews":"https://www.francetvinfo.fr/replay-jt/france-2/13-heures/jt-de-13h-du-jeudi-12-fevrier-2026_7758155.html","containsWordGlobalWarming":false}
{"title":"","description":"","date":"2026-02-14T15:46:00.886Z","order":9,"presenter":"Julian Bugier","authors":[""],"editor":"Elsa Pallot","editorDeputy":["Arnaud Comte","Margaux Manière","Julien Gasparutto"],"url":"","urlTvNews":"https://www.francetvinfo.fr/replay-jt/france-2/13-heures/jt-de-13h-du-jeudi-12-fevrier-2026_7758155.html","containsWordGlobalWarming":false}
{"title":"","description":"","date":"2026-02-14T15:46:00.981Z","order":10,"presenter":"Julian Bugier","authors":[""],"editor":"Elsa Pallot","editorDeputy":["Arnaud Comte","Margaux Manière","Julien Gasparutto"],"url":"","urlTvNews":"https://www.francetvinfo.fr/replay-jt/france-2/13-heures/jt-de-13h-du-jeudi-12-fevrier-2026_7758155.html","containsWordGlobalWarming":false}
{"title":"","description":"","date":"2026-02-14T15:46:01.054Z","order":11,"presenter":"Julian Bugier","authors":[""],"editor":"Elsa Pallot","editorDeputy":["Arnaud Comte","Margaux Manière","Julien Gasparutto"],"url":"","urlTvNews":"https://www.francetvinfo.fr/replay-jt/france-2/13-heures/jt-de-13h-du-jeudi-12-fevrier-2026_7758155.html","containsWordGlobalWarming":false}
{"title":"","description":"","date":"2026-02-14T15:46:01.134Z","order":12,"presenter":"Julian Bugier","authors":[""],"editor":"Elsa Pallot","editorDeputy":["Arnaud Comte","Margaux Manière","Julien Gasparutto"],"url":"","urlTvNews":"https://www.francetvinfo.fr/replay-jt/france-2/13-heures/jt-de-13h-du-jeudi-12-fevrier-2026_7758155.html","containsWordGlobalWarming":false}
